physionet/__init__.py
physionet/__main__.py
physionet/auth.py
physionet/cli.py
physionet/config.py
physionet/api/__init__.py
physionet/api/client.py
physionet/api/endpoints.py
physionet/api/exceptions.py
physionet/api/models.py
physionet/api/utils.py
physionet/datathon/__init__.py
physionet/datathon/mlhc.py
physionet/metrics/__init__.py
physionet/metrics/dimensions.py
physionet/metrics/openalex.py
physionet/project/__init__.py
physionet/project/loader.py
physionet/project/metadata.py
physionet/project/search.py
physionet/validate/__init__.py
physionet/validate/config.py
physionet/validate/models.py
physionet/validate/validator.py
physionet/validate/checks/__init__.py
physionet/validate/checks/documentation.py
physionet/validate/checks/filesystem.py
physionet/validate/checks/integrity.py
physionet/validate/checks/privacy.py
physionet/validate/checks/quality.py
physionet-0.1.5.dist-info/METADATA
physionet-0.1.5.dist-info/WHEEL
physionet-0.1.5.dist-info/entry_points.txt
physionet-0.1.5.dist-info/licenses/LICENSE
physionet-0.1.5.dist-info/RECORD
