Metadata-Version: 2.4
Name: physionet
Version: 0.1.5
Summary: A collection of tools for working with the PhysioNet repository.
Project-URL: homepage, https://github.com/MIT-LCP/physionet
Project-URL: repository, https://github.com/MIT-LCP/physionet
Author-email: Tom Pollard <tpollard@mit.edu>
License: The MIT License (MIT)
License-File: LICENSE
Keywords: dataset,medical,mimic,physionet
Classifier: License :: OSI Approved :: MIT License
Classifier: Operating System :: OS Independent
Classifier: Programming Language :: Python :: 3
Requires-Python: >=3.9
Requires-Dist: numpy
Requires-Dist: openpyxl
Requires-Dist: pandas
Requires-Dist: requests
Requires-Dist: tqdm
Provides-Extra: build
Requires-Dist: build>=0.10.0; extra == 'build'
Requires-Dist: twine>=4.0.0; extra == 'build'
Provides-Extra: dev
Requires-Dist: pytest>=7.0.0; extra == 'dev'
Requires-Dist: requests-mock>=1.9.0; extra == 'dev'
